deep_sort/__init__.py
deep_sort/deep_sort.py
deep_sort/deep/__init__.py
deep_sort/deep/evaluate.py
deep_sort/deep/feature_extractor.py
deep_sort/deep/model.py
deep_sort/deep/original_model.py
deep_sort/deep/test.py
deep_sort/deep/train.py
deep_sort/sort/__init__.py
deep_sort/sort/detection.py
deep_sort/sort/iou_matching.py
deep_sort/sort/kalman_filter.py
deep_sort/sort/linear_assignment.py
deep_sort/sort/nn_matching.py
deep_sort/sort/preprocessing.py
deep_sort/sort/track.py
deep_sort/sort/tracker.py
vhh_od/Classifier.py
vhh_od/Configuration.py
vhh_od/CustObject.py
vhh_od/OD.py
vhh_od/Shot.py
vhh_od/Video.py
vhh_od/__init__.py
vhh_od/augmentations.py
vhh_od/datasets.py
vhh_od/frame_processing.py
vhh_od/helpers.py
vhh_od/logger.py
vhh_od/parse_config.py
vhh_od/utils.py
vhh_od/visualize.py
vhh_od-1.5.3.dist-info/LICENSE
vhh_od-1.5.3.dist-info/METADATA
vhh_od-1.5.3.dist-info/WHEEL
vhh_od-1.5.3.dist-info/top_level.txt
vhh_od-1.5.3.dist-info/RECORD
