Metadata-Version: 2.1
Name: vhh-od
Version: 1.5.3
Summary: Object Detection and Tracking Package
Home-page: https://github.com/dahe-cvl/vhh_od
Author: Daniel Helm
Author-email: daniel.helm@tuwien.ac.at
License-File: LICENSE
Requires-Dist: torch (>=1.8.0)
Requires-Dist: torchvision (>=0.9.0)
Requires-Dist: matplotlib
Requires-Dist: opencv-python
Requires-Dist: numpy
Requires-Dist: tqdm
Requires-Dist: pyyaml
Requires-Dist: pillow
Requires-Dist: scipy
Requires-Dist: wandb
Requires-Dist: sklearn
Requires-Dist: pytorchyolo
